limesurvpy/__init__.py
limesurvpy/answer.py
limesurvpy/charting.py
limesurvpy/common.py
limesurvpy/data_processing.py
limesurvpy/item_set.py
limesurvpy/parser.py
limesurvpy/question.py
limesurvpy/response_set.py
limesurvpy/survey.py
limesurvpy/survey_item.py
limesurvpy/survey_structure.py
limesurvpy-0.0.4.dist-info/METADATA
limesurvpy-0.0.4.dist-info/WHEEL
limesurvpy-0.0.4.dist-info/top_level.txt
limesurvpy-0.0.4.dist-info/RECORD
